{
    "display": {
      "icon": {
        "item": "mysticdeep:earthcore_block"
      },
      "title": "Make an Earthcore block",
      "description": "The block from the Earth depths!",
      "frame": "task",
      "show_toast": true,
      "announce_to_chat": true
    },
    "parent": "mysticdeep:get_an_earthcore_ingot",
    "criteria": {
      "has_earthcore_block": {
        "trigger": "minecraft:inventory_changed",
        "conditions": {
          "items": [
            {
              "items": [
                "mysticdeep:earthcore_block"
              ]
            }
          ]
        }
      }
    },
    "sends_telemetry_event": false
  }
  