{
    "type": "minecraft:crafting_shaped",
    "pattern": [
        "S#S",
        "PYP",
        "PPP"
    ],
    "key": {
        "#": {
            "item": "mysticdeep:marinite_ingot"
        },
        "P": {
            "item": "mysticdeep:shadow_block"
        },
        "Y": {
            "item": "minecraft:dragon_egg"
        },
        "S": {
            "item": "minecraft:dragon_breath"
        }
    },
    "result": {
        "item": "mysticdeep:levraisteeltv_plush",
        "count": 1
    }
}